mycalc/calculator.py
Huggy_calc-0.0.1.dist-info/METADATA
Huggy_calc-0.0.1.dist-info/WHEEL
Huggy_calc-0.0.1.dist-info/top_level.txt
Huggy_calc-0.0.1.dist-info/RECORD
