Metadata-Version: 2.1
Name: Huggy-calc
Version: 0.0.1
Summary: oss-dev Huggy calculator 0001
Home-page: https://github.com/Huggy2646/calac0001
Download-URL: https://github.com/Huggy2646/calac0001/archive/refs/tags/v0.0.1.zip
Author: Seonghyeok Oh
Author-email: 1718772@donga.ac.kr
License: UNKNOWN
Platform: UNKNOWN
Classifier: Programming Language :: Python :: 3
